	<!--  merc novice  -->
    <specific_character id="sim_default_killer_0_default_0" team_default = "1">
    <name>GENERATE_NAME_stalker</name>
    <icon>ui_inGame2_merc_2</icon>
    <map_icon x="1" y="0"></map_icon>
    <bio>An experienced stalker. No other information available.</bio>
    <class>sim_default_killer_0</class>
    <community>killer</community> <terrain_sect>stalker_terrain</terrain_sect>
    <snd_config>characters_voice\human_03\killer\</snd_config>
    <rank>5947</rank>
    <money min="250" max="1750" infinitive="0"/>
    <reputation>1178</reputation>
    <visual>actors\stalker_merc\stalker_merc_2</visual>
    <supplies>
#include "gameplay\loadouts\killer\base.ltx"
#include "gameplay\loadouts\killer\tier_0.ltx"
		[spawn] \n
#include "gameplay\character_food.xml"
#include "gameplay\character_drugs.xml"
    </supplies>
#include "gameplay\character_criticals.xml"
#include "gameplay\character_dialogs.xml"
    </specific_character>
    
    <specific_character id="sim_default_killer_0_default_1" team_default = "1">
    <name>GENERATE_NAME_stalker</name>
    <icon>ui_inGame2_merc_2</icon>
    <map_icon x="1" y="0"></map_icon>
    <bio>An experienced stalker. No other information available.</bio>
    <class>sim_default_killer_0</class>
    <community>killer</community> <terrain_sect>stalker_terrain</terrain_sect>
    <snd_config>characters_voice\human_03\killer\</snd_config>
    <rank>5692</rank>
    <money min="250" max="1750" infinitive="0"/>
    <reputation>-752</reputation>
    <visual>actors\stalker_merc\stalker_merc2a</visual>
    <supplies>
#include "gameplay\loadouts\killer\base.ltx"
#include "gameplay\loadouts\killer\tier_0.ltx"
		[spawn] \n
#include "gameplay\character_food.xml"
#include "gameplay\character_drugs.xml"
    </supplies>
#include "gameplay\character_criticals.xml"
#include "gameplay\character_dialogs.xml"
    </specific_character>
    
    <specific_character id="sim_default_killer_0_default_2" team_default = "1">
    <name>GENERATE_NAME_stalker</name>
    <icon>ui_inGame2_merc_2</icon>
    <map_icon x="1" y="0"></map_icon>
    <bio>An experienced stalker. No other information available.</bio>
    <class>sim_default_killer_0</class>
    <community>killer</community> <terrain_sect>stalker_terrain</terrain_sect>
    <snd_config>characters_voice\human_03\killer\</snd_config>
    <rank>5693</rank>
    <money min="250" max="1750" infinitive="0"/>
    <reputation>1951</reputation>
    <visual>actors\stalker_merc\stalker_merc2b</visual>
    <supplies>
#include "gameplay\loadouts\killer\base.ltx"
#include "gameplay\loadouts\killer\tier_0.ltx"
		[spawn] \n
#include "gameplay\character_food.xml"
#include "gameplay\character_drugs.xml"
    </supplies>
#include "gameplay\character_criticals.xml"
#include "gameplay\character_dialogs.xml"
    </specific_character>
    
    <specific_character id="sim_default_killer_0_default_3" team_default = "1">
    <name>GENERATE_NAME_stalker</name>
    <icon>ui_inGame2_merc_2</icon>
    <map_icon x="1" y="0"></map_icon>
    <bio>An experienced stalker. No other information available.</bio>
    <class>sim_default_killer_0</class>
    <community>killer</community> <terrain_sect>stalker_terrain</terrain_sect>
    <snd_config>characters_voice\human_03\killer\</snd_config>
    <rank>5334</rank>
    <money min="250" max="1750" infinitive="0"/>
    <reputation>1140</reputation>
    <visual>actors\stalker_merc\stalker_merc2c</visual>
    <supplies>
#include "gameplay\loadouts\killer\base.ltx"
#include "gameplay\loadouts\killer\tier_0.ltx"
		[spawn] \n
#include "gameplay\character_food.xml"
#include "gameplay\character_drugs.xml"
    </supplies>
#include "gameplay\character_criticals.xml"
#include "gameplay\character_dialogs.xml"
    </specific_character>
    
    <specific_character id="sim_default_killer_0_default_4" team_default = "1">
    <name>GENERATE_NAME_stalker</name>
    <icon>ui_inGame2_mercen_2_mask</icon>
    <map_icon x="1" y="0"></map_icon>
    <bio>An experienced stalker. No other information available.</bio>
    <class>sim_default_killer_0</class>
    <community>killer</community> <terrain_sect>stalker_terrain</terrain_sect>
    <snd_config>characters_voice\human_03\killer\</snd_config>
    <rank>2683</rank>
    <money min="250" max="1750" infinitive="0"/>
    <reputation>-839</reputation>
    <visual>actors\stalker_merc\stalker_mercen_2_mask</visual>
    <supplies>
#include "gameplay\loadouts\killer\base.ltx"
#include "gameplay\loadouts\killer\tier_0.ltx"
		[spawn] \n
#include "gameplay\character_food.xml"
#include "gameplay\character_drugs.xml"
    </supplies>
#include "gameplay\character_criticals.xml"
#include "gameplay\character_dialogs.xml"
    </specific_character>
    
    <specific_character id="sim_default_killer_0_default_5" team_default = "1">
    <name>GENERATE_NAME_stalker</name>
    <icon>ui_inGame2_mercen_2_mask</icon>
    <map_icon x="1" y="0"></map_icon>
    <bio>An experienced stalker. No other information available.</bio>
    <class>sim_default_killer_0</class>
    <community>killer</community> <terrain_sect>stalker_terrain</terrain_sect>
    <snd_config>characters_voice\human_03\killer\</snd_config>
    <rank>2539</rank>
    <money min="250" max="1750" infinitive="0"/>
    <reputation>74</reputation>
    <visual>actors\stalker_merc\stalker_mercen2a_mask</visual>
    <supplies>
#include "gameplay\loadouts\killer\base.ltx"
#include "gameplay\loadouts\killer\tier_0.ltx"
		[spawn] \n
#include "gameplay\character_food.xml"
#include "gameplay\character_drugs.xml"
    </supplies>
#include "gameplay\character_criticals.xml"
#include "gameplay\character_dialogs.xml"
    </specific_character>
    
    <specific_character id="sim_default_killer_0_default_6" team_default = "1">
    <name>GENERATE_NAME_stalker</name>
    <icon>ui_inGame2_mercen_2_mask</icon>
    <map_icon x="1" y="0"></map_icon>
    <bio>An experienced stalker. No other information available.</bio>
    <class>sim_default_killer_0</class>
    <community>killer</community> <terrain_sect>stalker_terrain</terrain_sect>
    <snd_config>characters_voice\human_03\killer\</snd_config>
    <rank>1966</rank>
    <money min="250" max="1750" infinitive="0"/>
    <reputation>-1056</reputation>
    <visual>actors\stalker_merc\stalker_mercen2b_mask</visual>
    <supplies>
#include "gameplay\loadouts\killer\base.ltx"
#include "gameplay\loadouts\killer\tier_0.ltx"
		[spawn] \n
#include "gameplay\character_food.xml"
#include "gameplay\character_drugs.xml"
    </supplies>
#include "gameplay\character_criticals.xml"
#include "gameplay\character_dialogs.xml"
    </specific_character>
    
    <specific_character id="sim_default_killer_0_default_7" team_default = "1">
    <name>GENERATE_NAME_stalker</name>
    <icon>ui_inGame2_mercen_2_mask</icon>
    <map_icon x="1" y="0"></map_icon>
    <bio>An experienced stalker. No other information available.</bio>
    <class>sim_default_killer_0</class>
    <community>killer</community> <terrain_sect>stalker_terrain</terrain_sect>
    <snd_config>characters_voice\human_03\killer\</snd_config>
    <rank>2146</rank>
    <money min="250" max="1750" infinitive="0"/>
    <reputation>1400</reputation>
    <visual>actors\stalker_merc\stalker_mercen2c_mask</visual>
    <supplies>
#include "gameplay\loadouts\killer\base.ltx"
#include "gameplay\loadouts\killer\tier_0.ltx"
		[spawn] \n
#include "gameplay\character_food.xml"
#include "gameplay\character_drugs.xml"
    </supplies>
#include "gameplay\character_criticals.xml"
#include "gameplay\character_dialogs.xml"
    </specific_character>
    
    <specific_character id="sim_default_killer_0_default_8" team_default = "1">
    <name>GENERATE_NAME_stalker</name>
    <icon>ui_inGame2_merc_sun1</icon>
    <map_icon x="1" y="0"></map_icon>
    <bio>An experienced stalker. No other information available.</bio>
    <class>sim_default_killer_0</class>
    <community>killer</community> <terrain_sect>stalker_terrain</terrain_sect>
    <snd_config>characters_voice\human_03\killer\</snd_config>
    <rank>920</rank>
    <money min="250" max="1750" infinitive="0"/>
    <reputation>623</reputation>
    <visual>actors\stalker_merc\stalker_merc_sun1</visual>
    <supplies>
#include "gameplay\loadouts\killer\base.ltx"
#include "gameplay\loadouts\killer\tier_0.ltx"
		[spawn] \n
#include "gameplay\character_food.xml"
#include "gameplay\character_drugs.xml"
    </supplies>
#include "gameplay\character_criticals.xml"
#include "gameplay\character_dialogs.xml"
    </specific_character>
    
    <specific_character id="sim_default_killer_0_default_9" team_default = "1">
    <name>GENERATE_NAME_stalker</name>
    <icon>ui_inGame2_mercsun_old</icon>
    <map_icon x="1" y="0"></map_icon>
    <bio>An experienced stalker. No other information available.</bio>
    <class>sim_default_killer_0</class>
    <community>killer</community> <terrain_sect>stalker_terrain</terrain_sect>
    <snd_config>characters_voice\human_03\killer\</snd_config>
    <rank>5195</rank>
    <money min="250" max="1750" infinitive="0"/>
    <reputation>2462</reputation>
    <visual>actors\stalker_merc\stalker_merc_sun1_old</visual>
    <supplies>
#include "gameplay\loadouts\killer\base.ltx"
#include "gameplay\loadouts\killer\tier_0.ltx"
		[spawn] \n
#include "gameplay\character_food.xml"
#include "gameplay\character_drugs.xml"
    </supplies>
#include "gameplay\character_criticals.xml"
#include "gameplay\character_dialogs.xml"
    </specific_character>
    
    <specific_character id="sim_default_killer_0_default_10" team_default = "1">
    <name>GENERATE_NAME_stalker</name>
    <icon>ui_inGame2_merc_sun1_merc</icon>
    <map_icon x="1" y="0"></map_icon>
    <bio>An experienced stalker. No other information available.</bio>
    <class>sim_default_killer_0</class>
    <community>killer</community> <terrain_sect>stalker_terrain</terrain_sect>
    <snd_config>characters_voice\human_03\killer\</snd_config>
    <rank>7147</rank>
    <money min="250" max="1750" infinitive="0"/>
    <reputation>1927</reputation>
    <visual>actors\stalker_merc\stalker_merc_sun1_merc</visual>
    <supplies>
#include "gameplay\loadouts\killer\base.ltx"
#include "gameplay\loadouts\killer\tier_0.ltx"
		[spawn] \n
#include "gameplay\character_food.xml"
#include "gameplay\character_drugs.xml"
    </supplies>
#include "gameplay\character_criticals.xml"
#include "gameplay\character_dialogs.xml"
    </specific_character>
    
    <!--  merc expirienced  -->
    <specific_character id="sim_default_killer_1_default_0" team_default = "1">
    <name>GENERATE_NAME_stalker</name>
    <icon>ui_inGame2_merc_2</icon>
    <map_icon x="1" y="0"></map_icon>
    <bio>An experienced stalker. No other information available.</bio>
    <class>sim_default_killer_1</class>
    <community>killer</community> <terrain_sect>stalker_terrain</terrain_sect>
    <snd_config>characters_voice\human_03\killer\</snd_config>
    <rank>8414</rank>
    <money min="500" max="1750" infinitive="0"/>
    <reputation>1012</reputation>
    <visual>actors\stalker_merc\stalker_merc_2</visual>
    <supplies>
#include "gameplay\loadouts\killer\base.ltx"
#include "gameplay\loadouts\killer\tier_1.ltx"
		[spawn] \n
#include "gameplay\character_food.xml"
#include "gameplay\character_drugs_1.xml"
    </supplies>
#include "gameplay\character_criticals_1.xml"
#include "gameplay\character_dialogs.xml"
    </specific_character>
    
    <specific_character id="sim_default_killer_1_default_1" team_default = "1">
    <name>GENERATE_NAME_stalker</name>
    <icon>ui_inGame2_merc_2</icon>
    <map_icon x="1" y="0"></map_icon>
    <bio>An experienced stalker. No other information available.</bio>
    <class>sim_default_killer_1</class>
    <community>killer</community> <terrain_sect>stalker_terrain</terrain_sect>
    <snd_config>characters_voice\human_03\killer\</snd_config>
    <rank>9661</rank>
    <money min="500" max="1750" infinitive="0"/>
    <reputation>-67</reputation>
    <visual>actors\stalker_merc\stalker_merc2a</visual>
    <supplies>
#include "gameplay\loadouts\killer\base.ltx"
#include "gameplay\loadouts\killer\tier_1.ltx"
		[spawn] \n
#include "gameplay\character_food.xml"
#include "gameplay\character_drugs_1.xml"
    </supplies>
#include "gameplay\character_criticals_1.xml"
#include "gameplay\character_dialogs.xml"
    </specific_character>
    
    <specific_character id="sim_default_killer_1_default_2" team_default = "1">
    <name>GENERATE_NAME_stalker</name>
    <icon>ui_inGame2_merc_2</icon>
    <map_icon x="1" y="0"></map_icon>
    <bio>An experienced stalker. No other information available.</bio>
    <class>sim_default_killer_1</class>
    <community>killer</community> <terrain_sect>stalker_terrain</terrain_sect>
    <snd_config>characters_voice\human_03\killer\</snd_config>
    <rank>9283</rank>
    <money min="500" max="1750" infinitive="0"/>
    <reputation>-1168</reputation>
    <visual>actors\stalker_merc\stalker_merc2b</visual>
    <supplies>
#include "gameplay\loadouts\killer\base.ltx"
#include "gameplay\loadouts\killer\tier_1.ltx"
		[spawn] \n
#include "gameplay\character_food.xml"
#include "gameplay\character_drugs_1.xml"
    </supplies>
#include "gameplay\character_criticals_1.xml"
#include "gameplay\character_dialogs.xml"
    </specific_character>
    
    <specific_character id="sim_default_killer_1_default_3" team_default = "1">
    <name>GENERATE_NAME_stalker</name>
    <icon>ui_inGame2_merc_2</icon>
    <map_icon x="1" y="0"></map_icon>
    <bio>An experienced stalker. No other information available.</bio>
    <class>sim_default_killer_1</class>
    <community>killer</community> <terrain_sect>stalker_terrain</terrain_sect>
    <snd_config>characters_voice\human_03\killer\</snd_config>
    <rank>8362</rank>
    <money min="500" max="1750" infinitive="0"/>
    <reputation>1341</reputation>
    <visual>actors\stalker_merc\stalker_merc2c</visual>
    <supplies>
#include "gameplay\loadouts\killer\base.ltx"
#include "gameplay\loadouts\killer\tier_1.ltx"
		[spawn] \n
#include "gameplay\character_food.xml"
#include "gameplay\character_drugs_1.xml"
    </supplies>
#include "gameplay\character_criticals_1.xml"
#include "gameplay\character_dialogs.xml"
    </specific_character>
    
    <specific_character id="sim_default_killer_1_default_4" team_default = "1">
    <name>GENERATE_NAME_stalker</name>
    <icon>ui_inGame2_mercen_2_mask</icon>
    <map_icon x="1" y="0"></map_icon>
    <bio>An experienced stalker. No other information available.</bio>
    <class>sim_default_killer_1</class>
    <community>killer</community> <terrain_sect>stalker_terrain</terrain_sect>
    <snd_config>characters_voice\human_03\killer\</snd_config>
    <rank>9758</rank>
    <money min="500" max="1750" infinitive="0"/>
    <reputation>-568</reputation>
    <visual>actors\stalker_merc\stalker_mercen_2_mask</visual>
    <supplies>
#include "gameplay\loadouts\killer\base.ltx"
#include "gameplay\loadouts\killer\tier_1.ltx"
		[spawn] \n
#include "gameplay\character_food.xml"
#include "gameplay\character_drugs_1.xml"
    </supplies>
#include "gameplay\character_criticals_1.xml"
#include "gameplay\character_dialogs.xml"
    </specific_character>
    
    <specific_character id="sim_default_killer_1_default_5" team_default = "1">
    <name>GENERATE_NAME_stalker</name>
    <icon>ui_inGame2_mercen_2_mask</icon>
    <map_icon x="1" y="0"></map_icon>
    <bio>An experienced stalker. No other information available.</bio>
    <class>sim_default_killer_1</class>
    <community>killer</community> <terrain_sect>stalker_terrain</terrain_sect>
    <snd_config>characters_voice\human_03\killer\</snd_config>
    <rank>9588</rank>
    <money min="500" max="1750" infinitive="0"/>
    <reputation>-2470</reputation>
    <visual>actors\stalker_merc\stalker_mercen2a_mask</visual>
    <supplies>
#include "gameplay\loadouts\killer\base.ltx"
#include "gameplay\loadouts\killer\tier_1.ltx"
		[spawn] \n
#include "gameplay\character_food.xml"
#include "gameplay\character_drugs_1.xml"
    </supplies>
#include "gameplay\character_criticals_1.xml"
#include "gameplay\character_dialogs.xml"
    </specific_character>
    
    <specific_character id="sim_default_killer_1_default_6" team_default = "1">
    <name>GENERATE_NAME_stalker</name>
    <icon>ui_inGame2_mercen_2_mask</icon>
    <map_icon x="1" y="0"></map_icon>
    <bio>An experienced stalker. No other information available.</bio>
    <class>sim_default_killer_1</class>
    <community>killer</community> <terrain_sect>stalker_terrain</terrain_sect>
    <snd_config>characters_voice\human_03\killer\</snd_config>
    <rank>9869</rank>
    <money min="500" max="1750" infinitive="0"/>
    <reputation>-2294</reputation>
    <visual>actors\stalker_merc\stalker_mercen2b_mask</visual>
    <supplies>
#include "gameplay\loadouts\killer\base.ltx"
#include "gameplay\loadouts\killer\tier_1.ltx"
		[spawn] \n
#include "gameplay\character_food.xml"
#include "gameplay\character_drugs_1.xml"
    </supplies>
#include "gameplay\character_criticals_1.xml"
#include "gameplay\character_dialogs.xml"
    </specific_character>
    
    <specific_character id="sim_default_killer_1_default_7" team_default = "1">
    <name>GENERATE_NAME_stalker</name>
    <icon>ui_inGame2_mercen_2_mask</icon>
    <map_icon x="1" y="0"></map_icon>
    <bio>An experienced stalker. No other information available.</bio>
    <class>sim_default_killer_1</class>
    <community>killer</community> <terrain_sect>stalker_terrain</terrain_sect>
    <snd_config>characters_voice\human_03\killer\</snd_config>
    <rank>9648</rank>
    <money min="500" max="1750" infinitive="0"/>
    <reputation>-974</reputation>
    <visual>actors\stalker_merc\stalker_mercen2c_mask</visual>
    <supplies>
#include "gameplay\loadouts\killer\base.ltx"
#include "gameplay\loadouts\killer\tier_1.ltx"
		[spawn] \n
#include "gameplay\character_food.xml"
#include "gameplay\character_drugs_1.xml"
    </supplies>
#include "gameplay\character_criticals_1.xml"
#include "gameplay\character_dialogs.xml"
    </specific_character>
    
    <specific_character id="sim_default_killer_1_default_8" team_default = "1">
    <name>GENERATE_NAME_stalker</name>
    <icon>ui_inGame2_merc_sun1</icon>
    <map_icon x="1" y="0"></map_icon>
    <bio>An experienced stalker. No other information available.</bio>
    <class>sim_default_killer_1</class>
    <community>killer</community> <terrain_sect>stalker_terrain</terrain_sect>
    <snd_config>characters_voice\human_03\killer\</snd_config>
    <rank>8754</rank>
    <money min="500" max="1750" infinitive="0"/>
    <reputation>1594</reputation>
    <visual>actors\stalker_merc\stalker_merc_sun1</visual>
    <supplies>
#include "gameplay\loadouts\killer\base.ltx"
#include "gameplay\loadouts\killer\tier_1.ltx"
		[spawn] \n
#include "gameplay\character_food.xml"
#include "gameplay\character_drugs_1.xml"
    </supplies>
#include "gameplay\character_criticals_1.xml"
#include "gameplay\character_dialogs.xml"
    </specific_character>
    
    <specific_character id="sim_default_killer_1_default_9" team_default = "1">
    <name>GENERATE_NAME_stalker</name>
    <icon>ui_inGame2_mercsun_old</icon>
    <map_icon x="1" y="0"></map_icon>
    <bio>An experienced stalker. No other information available.</bio>
    <class>sim_default_killer_1</class>
    <community>killer</community> <terrain_sect>stalker_terrain</terrain_sect>
    <snd_config>characters_voice\human_03\killer\</snd_config>
    <rank>9635</rank>
    <money min="500" max="1750" infinitive="0"/>
    <reputation>2380</reputation>
    <visual>actors\stalker_merc\stalker_merc_sun1_old</visual>
    <supplies>
#include "gameplay\loadouts\killer\base.ltx"
#include "gameplay\loadouts\killer\tier_1.ltx"
		[spawn] \n
#include "gameplay\character_food.xml"
#include "gameplay\character_drugs_1.xml"
    </supplies>
#include "gameplay\character_criticals_1.xml"
#include "gameplay\character_dialogs.xml"
    </specific_character>
    
    <specific_character id="sim_default_killer_1_default_10" team_default = "1">
    <name>GENERATE_NAME_stalker</name>
    <icon>ui_inGame2_merc_sun1_merc</icon>
    <map_icon x="1" y="0"></map_icon>
    <bio>An experienced stalker. No other information available.</bio>
    <class>sim_default_killer_1</class>
    <community>killer</community> <terrain_sect>stalker_terrain</terrain_sect>
    <snd_config>characters_voice\human_03\killer\</snd_config>
    <rank>9208</rank>
    <money min="500" max="1750" infinitive="0"/>
    <reputation>-1785</reputation>
    <visual>actors\stalker_merc\stalker_merc_sun1_merc</visual>
    <supplies>
#include "gameplay\loadouts\killer\base.ltx"
#include "gameplay\loadouts\killer\tier_1.ltx"
		[spawn] \n
#include "gameplay\character_food.xml"
#include "gameplay\character_drugs_1.xml"
    </supplies>
#include "gameplay\character_criticals_1.xml"
#include "gameplay\character_dialogs.xml"
    </specific_character>
	
	<specific_character id="sim_default_killer_1_default_11" team_default = "1">
    <name>GENERATE_NAME_stalker</name>
    <icon>ui_inGame2_merc_sun1_merc</icon>
    <map_icon x="1" y="0"></map_icon>
    <bio>An experienced stalker. No other information available.</bio>
    <class>sim_default_killer_1</class>
    <community>killer</community> <terrain_sect>stalker_terrain</terrain_sect>
    <snd_config>characters_voice\human_03\killer\</snd_config>
    <rank>8208</rank>
    <money min="500" max="1750" infinitive="0"/>
    <reputation>-1785</reputation>
    <visual>actors\stalker_merc\stalker_merc_novice</visual>
    <supplies>
#include "gameplay\loadouts\killer\base.ltx"
#include "gameplay\loadouts\killer\tier_1.ltx"
		[spawn] \n
#include "gameplay\character_food.xml"
#include "gameplay\character_drugs_1.xml"
    </supplies>
#include "gameplay\character_criticals_1.xml"
#include "gameplay\character_dialogs.xml"
    </specific_character>
	
	<specific_character id="sim_default_killer_1_default_12" team_default = "1">
    <name>GENERATE_NAME_stalker</name>
    <icon>ui_inGame2_merc_sun1_merc</icon>
    <map_icon x="1" y="0"></map_icon>
    <bio>An experienced stalker. No other information available.</bio>
    <class>sim_default_killer_1</class>
    <community>killer</community> <terrain_sect>stalker_terrain</terrain_sect>
    <snd_config>characters_voice\human_03\killer\</snd_config>
    <rank>9208</rank>
    <money min="500" max="1750" infinitive="0"/>
    <reputation>-1785</reputation>
    <visual>actors\stalker_merc\stalker_merc_ps5m</visual>
    <supplies>
#include "gameplay\loadouts\killer\base.ltx"
#include "gameplay\loadouts\killer\tier_1.ltx"
		[spawn] \n
#include "gameplay\character_food.xml"
#include "gameplay\character_drugs_1.xml"
    </supplies>
#include "gameplay\character_criticals_1.xml"
#include "gameplay\character_dialogs.xml"
    </specific_character>
    
    <!--  merc expirienced 2  -->
    <specific_character id="sim_default_killer_2_default_0" team_default = "1">
    <name>GENERATE_NAME_stalker</name>
    <icon>ui_inGame2_merc_2</icon>
    <map_icon x="1" y="0"></map_icon>
    <bio>An experienced stalker. No other information available.</bio>
    <class>sim_default_killer_2</class>
    <community>killer</community> <terrain_sect>stalker_terrain</terrain_sect>
    <snd_config>characters_voice\human_03\killer\</snd_config>
    <rank>12775</rank>
    <money min="1500" max="2500" infinitive="0"/>
    <reputation>319</reputation>
    <visual>actors\stalker_merc\stalker_merc_2</visual>
    <supplies>
#include "gameplay\loadouts\killer\base.ltx"
#include "gameplay\loadouts\killer\tier_2.ltx"
		[spawn] \n
#include "gameplay\character_food.xml"
#include "gameplay\character_drugs_2.xml"
    </supplies>
#include "gameplay\character_criticals_2.xml"
#include "gameplay\character_dialogs.xml"
    </specific_character>
    
    <specific_character id="sim_default_killer_2_default_1" team_default = "1">
    <name>GENERATE_NAME_stalker</name>
    <icon>ui_inGame2_merc_2</icon>
    <map_icon x="1" y="0"></map_icon>
    <bio>An experienced stalker. No other information available.</bio>
    <class>sim_default_killer_2</class>
    <community>killer</community> <terrain_sect>stalker_terrain</terrain_sect>
    <snd_config>characters_voice\human_03\killer\</snd_config>
    <rank>12117</rank>
    <money min="1500" max="2500" infinitive="0"/>
    <reputation>1215</reputation>
    <visual>actors\stalker_merc\stalker_merc2a</visual>
    <supplies>
#include "gameplay\loadouts\killer\base.ltx"
#include "gameplay\loadouts\killer\tier_2.ltx"
		[spawn] \n
#include "gameplay\character_food.xml"
#include "gameplay\character_drugs_2.xml"
    </supplies>
#include "gameplay\character_criticals_2.xml"
#include "gameplay\character_dialogs.xml"
    </specific_character>
    
    <specific_character id="sim_default_killer_2_default_2" team_default = "1">
    <name>GENERATE_NAME_stalker</name>
    <icon>ui_inGame2_merc_2</icon>
    <map_icon x="1" y="0"></map_icon>
    <bio>An experienced stalker. No other information available.</bio>
    <class>sim_default_killer_2</class>
    <community>killer</community> <terrain_sect>stalker_terrain</terrain_sect>
    <snd_config>characters_voice\human_03\killer\</snd_config>
    <rank>12004</rank>
    <money min="1500" max="2500" infinitive="0"/>
    <reputation>2219</reputation>
    <visual>actors\stalker_merc\stalker_merc2b</visual>
    <supplies>
#include "gameplay\loadouts\killer\base.ltx"
#include "gameplay\loadouts\killer\tier_2.ltx"
		[spawn] \n
#include "gameplay\character_food.xml"
#include "gameplay\character_drugs_2.xml"
    </supplies>
#include "gameplay\character_criticals_2.xml"
#include "gameplay\character_dialogs.xml"
    </specific_character>
    
    <specific_character id="sim_default_killer_2_default_3" team_default = "1">
    <name>GENERATE_NAME_stalker</name>
    <icon>ui_inGame2_merc_2</icon>
    <map_icon x="1" y="0"></map_icon>
    <bio>An experienced stalker. No other information available.</bio>
    <class>sim_default_killer_2</class>
    <community>killer</community> <terrain_sect>stalker_terrain</terrain_sect>
    <snd_config>characters_voice\human_03\killer\</snd_config>
    <rank>12442</rank>
    <money min="1500" max="2500" infinitive="0"/>
    <reputation>2139</reputation>
    <visual>actors\stalker_merc\stalker_merc2c</visual>
    <supplies>
#include "gameplay\loadouts\killer\base.ltx"
#include "gameplay\loadouts\killer\tier_2.ltx"
		[spawn] \n
#include "gameplay\character_food.xml"
#include "gameplay\character_drugs_2.xml"
    </supplies>
#include "gameplay\character_criticals_2.xml"
#include "gameplay\character_dialogs.xml"
    </specific_character>
    
    <specific_character id="sim_default_killer_2_default_4" team_default = "1">
    <name>GENERATE_NAME_stalker</name>
    <icon>ui_inGame2_mercen_2_mask</icon>
    <map_icon x="1" y="0"></map_icon>
    <bio>An experienced stalker. No other information available.</bio>
    <class>sim_default_killer_2</class>
    <community>killer</community> <terrain_sect>stalker_terrain</terrain_sect>
    <snd_config>characters_voice\human_03\killer\</snd_config>
    <rank>12545</rank>
    <money min="1500" max="2500" infinitive="0"/>
    <reputation>471</reputation>
    <visual>actors\stalker_merc\stalker_mercen_2_mask</visual>
    <supplies>
#include "gameplay\loadouts\killer\base.ltx"
#include "gameplay\loadouts\killer\tier_2.ltx"
		[spawn] \n
#include "gameplay\character_food.xml"
#include "gameplay\character_drugs_2.xml"
    </supplies>
#include "gameplay\character_criticals_2.xml"
#include "gameplay\character_dialogs.xml"
    </specific_character>
    
    <specific_character id="sim_default_killer_2_default_5" team_default = "1">
    <name>GENERATE_NAME_stalker</name>
    <icon>ui_inGame2_mercen_2_mask</icon>
    <map_icon x="1" y="0"></map_icon>
    <bio>An experienced stalker. No other information available.</bio>
    <class>sim_default_killer_2</class>
    <community>killer</community> <terrain_sect>stalker_terrain</terrain_sect>
    <snd_config>characters_voice\human_03\killer\</snd_config>
    <rank>12463</rank>
    <money min="1500" max="2500" infinitive="0"/>
    <reputation>1128</reputation>
    <visual>actors\stalker_merc\stalker_mercen2a_mask</visual>
    <supplies>
#include "gameplay\loadouts\killer\base.ltx"
#include "gameplay\loadouts\killer\tier_2.ltx"
		[spawn] \n
#include "gameplay\character_food.xml"
#include "gameplay\character_drugs_2.xml"
    </supplies>
#include "gameplay\character_criticals_2.xml"
#include "gameplay\character_dialogs.xml"
    </specific_character>
    
    <specific_character id="sim_default_killer_2_default_6" team_default = "1">
    <name>GENERATE_NAME_stalker</name>
    <icon>ui_inGame2_mercen_2_mask</icon>
    <map_icon x="1" y="0"></map_icon>
    <bio>An experienced stalker. No other information available.</bio>
    <class>sim_default_killer_2</class>
    <community>killer</community> <terrain_sect>stalker_terrain</terrain_sect>
    <snd_config>characters_voice\human_03\killer\</snd_config>
    <rank>12748</rank>
    <money min="1500" max="2500" infinitive="0"/>
    <reputation>1985</reputation>
    <visual>actors\stalker_merc\stalker_mercen2b_mask</visual>
    <supplies>
#include "gameplay\loadouts\killer\base.ltx"
#include "gameplay\loadouts\killer\tier_2.ltx"
		[spawn] \n
#include "gameplay\character_food.xml"
#include "gameplay\character_drugs_2.xml"
    </supplies>
#include "gameplay\character_criticals_2.xml"
#include "gameplay\character_dialogs.xml"
    </specific_character>
    
    <specific_character id="sim_default_killer_2_default_7" team_default = "1">
    <name>GENERATE_NAME_stalker</name>
    <icon>ui_inGame2_mercen_2_mask</icon>
    <map_icon x="1" y="0"></map_icon>
    <bio>An experienced stalker. No other information available.</bio>
    <class>sim_default_killer_2</class>
    <community>killer</community> <terrain_sect>stalker_terrain</terrain_sect>
    <snd_config>characters_voice\human_03\killer\</snd_config>
    <rank>12885</rank>
    <money min="1500" max="2500" infinitive="0"/>
    <reputation>-1704</reputation>
    <visual>actors\stalker_merc\stalker_mercen2c_mask</visual>
    <supplies>
#include "gameplay\loadouts\killer\base.ltx"
#include "gameplay\loadouts\killer\tier_2.ltx"
		[spawn] \n
#include "gameplay\character_food.xml"
#include "gameplay\character_drugs_2.xml"
    </supplies>
#include "gameplay\character_criticals_2.xml"
#include "gameplay\character_dialogs.xml"
    </specific_character>
    
    <specific_character id="sim_default_killer_2_default_8" team_default = "1">
    <name>GENERATE_NAME_stalker</name>
    <icon>ui_inGame2_merc_sun1</icon>
    <map_icon x="1" y="0"></map_icon>
    <bio>An experienced stalker. No other information available.</bio>
    <class>sim_default_killer_2</class>
    <community>killer</community> <terrain_sect>stalker_terrain</terrain_sect>
    <snd_config>characters_voice\human_03\killer\</snd_config>
    <rank>12247</rank>
    <money min="1500" max="2500" infinitive="0"/>
    <reputation>21</reputation>
    <visual>actors\stalker_merc\stalker_merc_sun1</visual>
    <supplies>
#include "gameplay\loadouts\killer\base.ltx"
#include "gameplay\loadouts\killer\tier_2.ltx"
		[spawn] \n
#include "gameplay\character_food.xml"
#include "gameplay\character_drugs_2.xml"
    </supplies>
#include "gameplay\character_criticals_2.xml"
#include "gameplay\character_dialogs.xml"
    </specific_character>
    
    <specific_character id="sim_default_killer_2_default_9" team_default = "1">
    <name>GENERATE_NAME_stalker</name>
    <icon>ui_inGame2_mercsun_old</icon>
    <map_icon x="1" y="0"></map_icon>
    <bio>An experienced stalker. No other information available.</bio>
    <class>sim_default_killer_2</class>
    <community>killer</community> <terrain_sect>stalker_terrain</terrain_sect>
    <snd_config>characters_voice\human_03\killer\</snd_config>
    <rank>12816</rank>
    <money min="1500" max="2500" infinitive="0"/>
    <reputation>849</reputation>
    <visual>actors\stalker_merc\stalker_merc_sun1_old</visual>
    <supplies>
#include "gameplay\loadouts\killer\base.ltx"
#include "gameplay\loadouts\killer\tier_2.ltx"
		[spawn] \n
#include "gameplay\character_food.xml"
#include "gameplay\character_drugs_2.xml"
    </supplies>
#include "gameplay\character_criticals_2.xml"
#include "gameplay\character_dialogs.xml"
    </specific_character>
    
    <specific_character id="sim_default_killer_2_default_10" team_default = "1">
    <name>GENERATE_NAME_stalker</name>
    <icon>ui_inGame2_merc_sun1_merc</icon>
    <map_icon x="1" y="0"></map_icon>
    <bio>An experienced stalker. No other information available.</bio>
    <class>sim_default_killer_2</class>
    <community>killer</community> <terrain_sect>stalker_terrain</terrain_sect>
    <snd_config>characters_voice\human_03\killer\</snd_config>
    <rank>12682</rank>
    <money min="1500" max="2500" infinitive="0"/>
    <reputation>-2404</reputation>
    <visual>actors\stalker_merc\stalker_merc_sun1_merc</visual>
    <supplies>
#include "gameplay\loadouts\killer\base.ltx"
#include "gameplay\loadouts\killer\tier_2.ltx"
		[spawn] \n
#include "gameplay\character_food.xml"
#include "gameplay\character_drugs_2.xml"
    </supplies>
#include "gameplay\character_criticals_2.xml"
#include "gameplay\character_dialogs.xml"
    </specific_character>
    
	<specific_character id="sim_default_killer_2_default_11" team_default = "1">
    <name>GENERATE_NAME_stalker</name>
    <icon>ui_inGame2_merc_sun1_merc</icon>
    <map_icon x="1" y="0"></map_icon>
    <bio>An experienced stalker. No other information available.</bio>
    <class>sim_default_killer_2</class>
    <community>killer</community> <terrain_sect>stalker_terrain</terrain_sect>
    <snd_config>characters_voice\human_03\killer\</snd_config>
    <rank>13682</rank>
    <money min="1500" max="2500" infinitive="0"/>
    <reputation>-2404</reputation>
    <visual>actors\stalker_merc\stalker_mercen_2_france</visual>
    <supplies>
#include "gameplay\loadouts\killer\base.ltx"
#include "gameplay\loadouts\killer\tier_2.ltx"
		[spawn] \n
#include "gameplay\character_food.xml"
#include "gameplay\character_drugs_2.xml"
    </supplies>
#include "gameplay\character_criticals_2.xml"
#include "gameplay\character_dialogs.xml"
    </specific_character>
	
	<specific_character id="sim_default_killer_2_default_12" team_default = "1">
    <name>GENERATE_NAME_stalker</name>
    <icon>ui_inGame2_merc_sun1_merc</icon>
    <map_icon x="1" y="0"></map_icon>
    <bio>An experienced stalker. No other information available.</bio>
    <class>sim_default_killer_2</class>
    <community>killer</community> <terrain_sect>stalker_terrain</terrain_sect>
    <snd_config>characters_voice\human_03\killer\</snd_config>
    <rank>12682</rank>
    <money min="1500" max="2500" infinitive="0"/>
    <reputation>-2404</reputation>
    <visual>actors\stalker_merc\stalker_merc_usa</visual>
    <supplies>
#include "gameplay\loadouts\killer\base.ltx"
#include "gameplay\loadouts\killer\tier_2.ltx"
		[spawn] \n
#include "gameplay\character_food.xml"
#include "gameplay\character_drugs_2.xml"
    </supplies>
#include "gameplay\character_criticals_2.xml"
#include "gameplay\character_dialogs.xml"
    </specific_character>
	
	<specific_character id="sim_default_killer_2_default_13" team_default = "1">
    <name>GENERATE_NAME_stalker</name>
    <icon>ui_inGame2_merc_sun1_merc</icon>
    <map_icon x="1" y="0"></map_icon>
    <bio>An experienced stalker. No other information available.</bio>
    <class>sim_default_killer_2</class>
    <community>killer</community> <terrain_sect>stalker_terrain</terrain_sect>
    <snd_config>characters_voice\human_03\killer\</snd_config>
    <rank>13682</rank>
    <money min="1500" max="2500" infinitive="0"/>
    <reputation>-2404</reputation>
    <visual>actors\stalker_merc\mp_team_blue_addon_de</visual>
    <supplies>
#include "gameplay\loadouts\killer\base.ltx"
#include "gameplay\loadouts\killer\tier_2.ltx"
		[spawn] \n
#include "gameplay\character_food.xml"
#include "gameplay\character_drugs_2.xml"
    </supplies>
#include "gameplay\character_criticals_2.xml"
#include "gameplay\character_dialogs.xml"
    </specific_character>
	
	<specific_character id="sim_default_killer_2_default_14" team_default = "1">
    <name>GENERATE_NAME_stalker</name>
    <icon>ui_inGame2_merc_sun1_merc</icon>
    <map_icon x="1" y="0"></map_icon>
    <bio>An experienced stalker. No other information available.</bio>
    <class>sim_default_killer_2</class>
    <community>killer</community> <terrain_sect>stalker_terrain</terrain_sect>
    <snd_config>characters_voice\human_03\killer\</snd_config>
    <rank>12682</rank>
    <money min="1500" max="2500" infinitive="0"/>
    <reputation>-2404</reputation>
    <visual>actors\stalker_merc\mp_team_green_addon_fr</visual>
    <supplies>
#include "gameplay\loadouts\killer\base.ltx"
#include "gameplay\loadouts\killer\tier_2.ltx"
		[spawn] \n
#include "gameplay\character_food.xml"
#include "gameplay\character_drugs_2.xml"
    </supplies>
#include "gameplay\character_criticals_2.xml"
#include "gameplay\character_dialogs.xml"
    </specific_character>
	
	<specific_character id="sim_default_killer_2_default_15" team_default = "1">
    <name>GENERATE_NAME_stalker</name>
    <icon>ui_inGame2_merc_sun1_merc</icon>
    <map_icon x="1" y="0"></map_icon>
    <bio>An experienced stalker. No other information available.</bio>
    <class>sim_default_killer_2</class>
    <community>killer</community> <terrain_sect>stalker_terrain</terrain_sect>
    <snd_config>characters_voice\human_03\killer\</snd_config>
    <rank>13682</rank>
    <money min="1500" max="2500" infinitive="0"/>
    <reputation>-2404</reputation>
    <visual>actors\stalker_merc\mp_team_green_addon_uk</visual>
    <supplies>
#include "gameplay\loadouts\killer\base.ltx"
#include "gameplay\loadouts\killer\tier_2.ltx"
		[spawn] \n
#include "gameplay\character_food.xml"
#include "gameplay\character_drugs_2.xml"
    </supplies>
#include "gameplay\character_criticals_2.xml"
#include "gameplay\character_dialogs.xml"
    </specific_character>
	
	<specific_character id="sim_default_killer_2_default_16" team_default = "1">
    <name>GENERATE_NAME_stalker</name>
    <icon>ui_inGame2_merc_sun1_merc</icon>
    <map_icon x="1" y="0"></map_icon>
    <bio>An experienced stalker. No other information available.</bio>
    <class>sim_default_killer_2</class>
    <community>killer</community> <terrain_sect>stalker_terrain</terrain_sect>
    <snd_config>characters_voice\human_03\killer\</snd_config>
    <rank>12682</rank>
    <money min="1500" max="2500" infinitive="0"/>
    <reputation>-2404</reputation>
    <visual>actors\stalker_merc\mp_team_blue_addon_de</visual>
    <supplies>
#include "gameplay\loadouts\killer\base.ltx"
#include "gameplay\loadouts\killer\tier_2.ltx"
		[spawn] \n
#include "gameplay\character_food.xml"
#include "gameplay\character_drugs_2.xml"
    </supplies>
#include "gameplay\character_criticals_2.xml"
#include "gameplay\character_dialogs.xml"
    </specific_character>
	
    <!--  merc veteran  -->
    <specific_character id="sim_default_killer_3_default_0" team_default = "1">
    <name>GENERATE_NAME_stalker</name>
    <icon>ui_inGame2_mercenary3</icon>
    <map_icon x="1" y="0"></map_icon>
    <bio>An experienced stalker. No other information available.</bio>
    <class>sim_default_killer_3</class>
    <community>killer</community> <terrain_sect>stalker_terrain</terrain_sect>
    <snd_config>characters_voice\human_03\killer\</snd_config>
    <rank>18133</rank>
    <money min="2500" max="5000" infinitive="0"/>
    <reputation>1108</reputation>
    <visual>actors\stalker_merc\stalker_mercenary3</visual>
    <supplies>
#include "gameplay\loadouts\killer\base.ltx"
#include "gameplay\loadouts\killer\tier_3.ltx"
		[spawn] \n
#include "gameplay\character_food.xml"
#include "gameplay\character_drugs_2.xml"
    </supplies>
#include "gameplay\character_criticals_3.xml"
#include "gameplay\character_dialogs.xml"
    </specific_character>
    
    <specific_character id="sim_default_killer_3_default_1" team_default = "1">
    <name>GENERATE_NAME_stalker</name>
    <icon>ui_inGame2_mercenary3</icon>
    <map_icon x="1" y="0"></map_icon>
    <bio>An experienced stalker. No other information available.</bio>
    <class>sim_default_killer_3</class>
    <community>killer</community> <terrain_sect>stalker_terrain</terrain_sect>
    <snd_config>characters_voice\human_03\killer\</snd_config>
    <rank>18753</rank>
    <money min="2500" max="5000" infinitive="0"/>
    <reputation>-163</reputation>
    <visual>actors\stalker_merc\stalker_mercenary4</visual>
    <supplies>
#include "gameplay\loadouts\killer\base.ltx"
#include "gameplay\loadouts\killer\tier_3.ltx"
		[spawn] \n
#include "gameplay\character_food.xml"
#include "gameplay\character_drugs_2.xml"
    </supplies>
#include "gameplay\character_criticals_3.xml"
#include "gameplay\character_dialogs.xml"
    </specific_character>
    
    <specific_character id="sim_default_killer_3_default_2" team_default = "1">
    <name>GENERATE_NAME_stalker</name>
    <icon>ui_inGame2_mercenary3</icon>
    <map_icon x="1" y="0"></map_icon>
    <bio>An experienced stalker. No other information available.</bio>
    <class>sim_default_killer_3</class>
    <community>killer</community> <terrain_sect>stalker_terrain</terrain_sect>
    <snd_config>characters_voice\human_03\killer\</snd_config>
    <rank>16312</rank>
    <money min="2500" max="5000" infinitive="0"/>
    <reputation>1441</reputation>
    <visual>actors\stalker_merc\stalker_mercenary3</visual>
    <supplies>
#include "gameplay\loadouts\killer\base.ltx"
#include "gameplay\loadouts\killer\tier_3.ltx"
		[spawn] \n
#include "gameplay\character_food.xml"
#include "gameplay\character_drugs_2.xml"
    </supplies>
#include "gameplay\character_criticals_3.xml"
#include "gameplay\character_dialogs.xml"
    </specific_character>
    
    <specific_character id="sim_default_killer_3_default_3" team_default = "1">
    <name>GENERATE_NAME_stalker</name>
    <icon>ui_inGame2_mercenary3</icon>
    <map_icon x="1" y="0"></map_icon>
    <bio>An experienced stalker. No other information available.</bio>
    <class>sim_default_killer_3</class>
    <community>killer</community> <terrain_sect>stalker_terrain</terrain_sect>
    <snd_config>characters_voice\human_03\killer\</snd_config>
    <rank>16465</rank>
    <money min="2500" max="5000" infinitive="0"/>
    <reputation>527</reputation>
    <visual>actors\stalker_merc\stalker_mercenary4</visual>
    <supplies>
#include "gameplay\loadouts\killer\base.ltx"
#include "gameplay\loadouts\killer\tier_3.ltx"
		[spawn] \n
#include "gameplay\character_food.xml"
#include "gameplay\character_drugs_2.xml"
    </supplies>
#include "gameplay\character_criticals_3.xml"
#include "gameplay\character_dialogs.xml"
    </specific_character>
    
    <specific_character id="sim_default_killer_3_default_4" team_default = "1">
    <name>GENERATE_NAME_stalker</name>
    <icon>ui_inGame2_merc_4</icon>
    <map_icon x="1" y="0"></map_icon>
    <bio>An experienced stalker. No other information available.</bio>
    <class>sim_default_killer_3</class>
    <community>killer</community> <terrain_sect>stalker_terrain</terrain_sect>
    <snd_config>characters_voice\human_03\killer\</snd_config>
    <rank>18856</rank>
    <money min="2500" max="5000" infinitive="0"/>
    <reputation>-1438</reputation>
    <visual>actors\stalker_merc\stalker_merc_4</visual>
    <supplies>
#include "gameplay\loadouts\killer\base.ltx"
#include "gameplay\loadouts\killer\tier_3.ltx"
		[spawn] \n
#include "gameplay\character_food.xml"
#include "gameplay\character_drugs_2.xml"
    </supplies>
#include "gameplay\character_criticals_3.xml"
#include "gameplay\character_dialogs.xml"
    </specific_character>
    
    <specific_character id="sim_default_killer_3_default_5" team_default = "1">
    <name>GENERATE_NAME_stalker</name>
    <icon>ui_inGame2_merc_4</icon>
    <map_icon x="1" y="0"></map_icon>
    <bio>An experienced stalker. No other information available.</bio>
    <class>sim_default_killer_3</class>
    <community>killer</community> <terrain_sect>stalker_terrain</terrain_sect>
    <snd_config>characters_voice\human_03\killer\</snd_config>
    <rank>16782</rank>
    <money min="2500" max="5000" infinitive="0"/>
    <reputation>-1276</reputation>
    <visual>actors\stalker_merc\stalker_merc4a</visual>
    <supplies>
#include "gameplay\loadouts\killer\base.ltx"
#include "gameplay\loadouts\killer\tier_3.ltx"
		[spawn] \n
#include "gameplay\character_food.xml"
#include "gameplay\character_drugs_2.xml"
    </supplies>
#include "gameplay\character_criticals_3.xml"
#include "gameplay\character_dialogs.xml"
    </specific_character>
    
    <specific_character id="sim_default_killer_3_default_6" team_default = "1">
    <name>GENERATE_NAME_stalker</name>
    <icon>ui_inGame2_merc_4a</icon>
    <map_icon x="1" y="0"></map_icon>
    <bio>An experienced stalker. No other information available.</bio>
    <class>sim_default_killer_3</class>
    <community>killer</community> <terrain_sect>stalker_terrain</terrain_sect>
    <snd_config>characters_voice\human_03\killer\</snd_config>
    <rank>17705</rank>
    <money min="2500" max="5000" infinitive="0"/>
    <reputation>2071</reputation>
    <visual>actors\stalker_merc\stalker_mercexo_4</visual>
    <supplies>
#include "gameplay\loadouts\killer\base.ltx"
#include "gameplay\loadouts\killer\tier_3.ltx"
		[spawn] \n
#include "gameplay\character_food.xml"
#include "gameplay\character_drugs_2.xml"
    </supplies>
#include "gameplay\character_criticals_3.xml"
#include "gameplay\character_dialogs.xml"
    </specific_character>
    
    <specific_character id="sim_default_killer_3_default_7" team_default = "1">
    <name>GENERATE_NAME_stalker</name>
    <icon>ui_inGame2_merc_4a</icon>
    <map_icon x="1" y="0"></map_icon>
    <bio>An experienced stalker. No other information available.</bio>
    <class>sim_default_killer_3</class>
    <community>killer</community> <terrain_sect>stalker_terrain</terrain_sect>
    <snd_config>characters_voice\human_03\killer\</snd_config>
    <rank>19124</rank>
    <money min="2500" max="5000" infinitive="0"/>
    <reputation>147</reputation>
    <visual>actors\stalker_merc\stalker_mercexo4a</visual>
    <supplies>
#include "gameplay\loadouts\killer\base.ltx"
#include "gameplay\loadouts\killer\tier_3.ltx"
		[spawn] \n
#include "gameplay\character_food.xml"
#include "gameplay\character_drugs_2.xml"
    </supplies>
#include "gameplay\character_criticals_3.xml"
#include "gameplay\character_dialogs.xml"
    </specific_character>
    
    <!--  merc master  -->
    <specific_character id="sim_default_killer_4_default_0" team_default = "1">
    <name>GENERATE_NAME_stalker</name>
    <icon>ui_inGame2_merc_4</icon>
    <map_icon x="1" y="0"></map_icon>
    <bio>An experienced stalker. No other information available.</bio>
    <class>sim_default_killer_4</class>
    <community>killer</community> <terrain_sect>stalker_terrain</terrain_sect>
    <snd_config>characters_voice\human_03\killer\</snd_config>
    <rank>22193</rank>
    <money min="5000" max="10000" infinitive="0"/>
    <reputation>-1079</reputation>
    <visual>actors\stalker_merc\stalker_merc_4</visual>
    <supplies>
#include "gameplay\loadouts\killer\base.ltx"
#include "gameplay\loadouts\killer\tier_4.ltx"
		[spawn] \n
#include "gameplay\character_food.xml"
#include "gameplay\character_drugs_4.xml"
    </supplies>
#include "gameplay\character_criticals_4.xml"
#include "gameplay\character_dialogs.xml"
    </specific_character>
    
    <specific_character id="sim_default_killer_4_default_1" team_default = "1">
    <name>GENERATE_NAME_stalker</name>
    <icon>ui_inGame2_merc_4</icon>
    <map_icon x="1" y="0"></map_icon>
    <bio>An experienced stalker. No other information available.</bio>
    <class>sim_default_killer_4</class>
    <community>killer</community> <terrain_sect>stalker_terrain</terrain_sect>
    <snd_config>characters_voice\human_03\killer\</snd_config>
    <rank>20731</rank>
    <money min="5000" max="10000" infinitive="0"/>
    <reputation>-715</reputation>
    <visual>actors\stalker_merc\stalker_merc4a</visual>
    <supplies>
#include "gameplay\loadouts\killer\base.ltx"
#include "gameplay\loadouts\killer\tier_4.ltx"
		[spawn] \n
#include "gameplay\character_food.xml"
#include "gameplay\character_drugs_4.xml"
    </supplies>
#include "gameplay\character_criticals_4.xml"
#include "gameplay\character_dialogs.xml"
    </specific_character>
    
    <specific_character id="sim_default_killer_4_default_2" team_default = "1">
    <name>GENERATE_NAME_stalker</name>
    <icon>ui_inGame2_merc_4a</icon>
    <map_icon x="1" y="0"></map_icon>
    <bio>An experienced stalker. No other information available.</bio>
    <class>sim_default_killer_4</class>
    <community>killer</community> <terrain_sect>stalker_terrain</terrain_sect>
    <snd_config>characters_voice\human_03\killer\</snd_config>
    <rank>22811</rank>
    <money min="5000" max="10000" infinitive="0"/>
    <reputation>743</reputation>
    <visual>actors\stalker_merc\stalker_mercexo_4</visual>
    <supplies>
#include "gameplay\loadouts\killer\base.ltx"
#include "gameplay\loadouts\killer\tier_4.ltx"
		[spawn] \n
#include "gameplay\character_food.xml"
#include "gameplay\character_drugs_4.xml"
    </supplies>
#include "gameplay\character_criticals_4.xml"
#include "gameplay\character_dialogs.xml"
    </specific_character>
    
    <specific_character id="sim_default_killer_4_default_3" team_default = "1">
    <name>GENERATE_NAME_stalker</name>
    <icon>ui_inGame2_merc_4a</icon>
    <map_icon x="1" y="0"></map_icon>
    <bio>An experienced stalker. No other information available.</bio>
    <class>sim_default_killer_4</class>
    <community>killer</community> <terrain_sect>stalker_terrain</terrain_sect>
    <snd_config>characters_voice\human_03\killer\</snd_config>
    <rank>20437</rank>
    <money min="5000" max="10000" infinitive="0"/>
    <reputation>-635</reputation>
    <visual>actors\stalker_merc\stalker_mercexo4a</visual>
    <supplies>
#include "gameplay\loadouts\killer\base.ltx"
#include "gameplay\loadouts\killer\tier_4.ltx"
		[spawn] \n
#include "gameplay\character_food.xml"
#include "gameplay\character_drugs_4.xml"
    </supplies>
#include "gameplay\character_criticals_4.xml"
#include "gameplay\character_dialogs.xml"
    </specific_character>
    
	<specific_character id="sim_default_killer_4_default_4" team_default = "1">
    <name>GENERATE_NAME_stalker</name>
    <icon>ui_inGame2_merc_4a</icon>
    <map_icon x="1" y="0"></map_icon>
    <bio>An experienced stalker. No other information available.</bio>
    <class>sim_default_killer_4</class>
    <community>killer</community> <terrain_sect>stalker_terrain</terrain_sect>
    <snd_config>characters_voice\human_03\killer\</snd_config>
    <rank>20437</rank>
    <money min="5000" max="10000" infinitive="0"/>
    <reputation>-635</reputation>
    <visual>actors\stalker_merc\stalker_merc_military</visual>
    <supplies>
#include "gameplay\loadouts\killer\base.ltx"
#include "gameplay\loadouts\killer\tier_4.ltx"
		[spawn] \n
#include "gameplay\character_food.xml"
#include "gameplay\character_drugs_4.xml"
    </supplies>
#include "gameplay\character_criticals_4.xml"
#include "gameplay\character_dialogs.xml"
    </specific_character>
	
	<specific_character id="sim_default_killer_4_default_5" team_default = "1">
    <name>GENERATE_NAME_stalker</name>
    <icon>ui_inGame2_blue_exo_proto</icon>
    <map_icon x="1" y="0"></map_icon>
    <bio>An experienced stalker. No other information available.</bio>
    <class>sim_default_killer_4</class>
    <community>killer</community> <terrain_sect>stalker_terrain</terrain_sect>
    <snd_config>characters_voice\human_03\killer\</snd_config>
    <rank>20437</rank>
    <money min="5000" max="10000" infinitive="0"/>
    <reputation>-635</reputation>
    <visual>actors\stalker_merc\stalker_merc_exo_proto</visual>
    <supplies>
#include "gameplay\loadouts\killer\base.ltx"
#include "gameplay\loadouts\killer\tier_4.ltx"
		[spawn] \n
#include "gameplay\character_food.xml"
#include "gameplay\character_drugs_4.xml"
    </supplies>
#include "gameplay\character_criticals_4.xml"
#include "gameplay\character_dialogs.xml"
    </specific_character>
	
	<specific_character id="sim_default_killer_4_default_6" team_default = "1">
    <name>GENERATE_NAME_stalker</name>
    <icon>ui_inGame2_blue_exo_proto</icon>
    <map_icon x="1" y="0"></map_icon>
    <bio>An experienced stalker. No other information available.</bio>
    <class>sim_default_killer_4</class>
    <community>killer</community> <terrain_sect>stalker_terrain</terrain_sect>
    <snd_config>characters_voice\human_03\killer\</snd_config>
    <rank>22437</rank>
    <money min="5000" max="10000" infinitive="0"/>
    <reputation>3635</reputation>
    <visual>actors\my\seva_merc</visual>
    <supplies>
#include "gameplay\loadouts\killer\base.ltx"
#include "gameplay\loadouts\killer\tier_4.ltx"
		[spawn] \n
#include "gameplay\character_food.xml"
#include "gameplay\character_drugs_4.xml"
    </supplies>
#include "gameplay\character_criticals_4.xml"
#include "gameplay\character_dialogs.xml"
    </specific_character>
		